Classfile /home/psi/Dropbox/src/haskell/java.js/sample/pi/Pi.class
  Last modified Aug 14, 2015; size 474 bytes
  MD5 checksum 309e8af62b163f0da79d25eb01e8ce37
  Compiled from "Pi.java"
public class Pi
  minor version: 0
  major version: 50
  flags: ACC_PUBLIC, ACC_SUPER
Constant pool:
   #1 = Methodref          #12.#24        // java/lang/Object."<init>":()V
   #2 = Double             16.0d
   #4 = Double             0.2d
   #6 = Methodref          #11.#25        // Pi.arcTan:(D)D
   #7 = Double             4.0d
   #9 = Double             0.0041841004184100415d
  #11 = Class              #26            // Pi
  #12 = Class              #27            // java/lang/Object
  #13 = Utf8               <init>
  #14 = Utf8               ()V
  #15 = Utf8               Code
  #16 = Utf8               LineNumberTable
  #17 = Utf8               calc
  #18 = Utf8               ()D
  #19 = Utf8               arcTan
  #20 = Utf8               (D)D
  #21 = Utf8               StackMapTable
  #22 = Utf8               SourceFile
  #23 = Utf8               Pi.java
  #24 = NameAndType        #13:#14        // "<init>":()V
  #25 = NameAndType        #19:#20        // arcTan:(D)D
  #26 = Utf8               Pi
  #27 = Utf8               java/lang/Object
{
  public Pi();
    descriptor: ()V
    flags: ACC_PUBLIC
    Code:
      stack=1, locals=1, args_size=1
         0: aload_0
         1: invokespecial #1                  // Method java/lang/Object."<init>":()V
         4: return
      LineNumberTable:
        line 1: 0

  public static double calc();
    descriptor: ()D
    flags: ACC_PUBLIC, ACC_STATIC
    Code:
      stack=6, locals=2, args_size=0
         0: ldc2_w        #2                  // double 16.0d
         3: ldc2_w        #4                  // double 0.2d
         6: invokestatic  #6                  // Method arcTan:(D)D
         9: dmul
        10: ldc2_w        #7                  // double 4.0d
        13: ldc2_w        #9                  // double 0.0041841004184100415d
        16: invokestatic  #6                  // Method arcTan:(D)D
        19: dmul
        20: dsub
        21: dstore_0
        22: dload_0
        23: dreturn
      LineNumberTable:
        line 4: 0
        line 5: 22

  private static double arcTan(double);
    descriptor: (D)D
    flags: ACC_PRIVATE, ACC_STATIC
    Code:
      stack=6, locals=9, args_size=1
         0: dconst_0
         1: dstore_2
         2: dload_0
         3: dstore        4
         5: dload_0
         6: dload_0
         7: dmul
         8: dstore        6
        10: iconst_0
        11: istore        8
        13: dload         4
        15: dconst_0
        16: dcmpl
        17: ifeq          48
        20: dload_2
        21: dload         4
        23: iload         8
        25: iload         8
        27: iadd
        28: iconst_1
        29: iadd
        30: i2d
        31: ddiv
        32: dadd
        33: dstore_2
        34: dload         4
        36: dneg
        37: dload         6
        39: dmul
        40: dstore        4
        42: iinc          8, 1
        45: goto          13
        48: dload_2
        49: dreturn
      LineNumberTable:
        line 9: 0
        line 10: 2
        line 11: 5
        line 12: 10
        line 13: 20
        line 14: 34
        line 12: 42
        line 16: 48
      StackMapTable: number_of_entries = 2
        frame_type = 255 /* full_frame */
          offset_delta = 13
          locals = [ double, double, double, double, int ]
          stack = []
        frame_type = 250 /* chop */
          offset_delta = 34
}
SourceFile: "Pi.java"
